keirolabs/__init__.py
keirolabs/client.py
keirolabs/exceptions.py
keirolabs-0.1.5.dist-info/licenses/LICENSE
keirolabs-0.1.5.dist-info/METADATA
keirolabs-0.1.5.dist-info/WHEEL
keirolabs-0.1.5.dist-info/top_level.txt
keirolabs-0.1.5.dist-info/RECORD
