Metadata-Version: 2.4
Name: keirolabs
Version: 0.1.5
Summary: Official Python SDK for KeiroLabs API - Search, Research, and Web Crawling
Author-email: KeiroLabs Team <support@keiro.com>
License: MIT
Project-URL: Homepage, https://www.keirolabs.cloud/
Project-URL: Documentation, https://www.keirolabs.cloud/docs
Project-URL: Repository, https://github.com/yourusername/keiro-python-sdk
Project-URL: Bug Tracker, https://github.com/yourusername/keiro-python-sdk/issues
Keywords: keirolabs,keiro,api,search,research,web-crawler,sdk,ai-search
Classifier: Development Status :: 3 - Alpha
Classifier: Intended Audience :: Developers
Classifier: License :: OSI Approved :: MIT License
Classifier: Programming Language :: Python :: 3
Classifier: Programming Language :: Python :: 3.7
Classifier: Programming Language :: Python :: 3.8
Classifier: Programming Language :: Python :: 3.9
Classifier: Programming Language :: Python :: 3.10
Classifier: Programming Language :: Python :: 3.11
Classifier: Programming Language :: Python :: 3.12
Classifier: Topic :: Software Development :: Libraries :: Python Modules
Classifier: Topic :: Internet :: WWW/HTTP
Requires-Python: >=3.7
License-File: LICENSE
Requires-Dist: requests>=2.28.0
Provides-Extra: dev
Requires-Dist: pytest>=7.0.0; extra == "dev"
Requires-Dist: pytest-cov>=4.0.0; extra == "dev"
Requires-Dist: black>=22.0.0; extra == "dev"
Requires-Dist: flake8>=5.0.0; extra == "dev"
Requires-Dist: mypy>=0.990; extra == "dev"
Dynamic: license-file
Dynamic: requires-python
